ninpol/__init__.py
ninpol/_interpolator/__init__.pxd
ninpol/_interpolator/grid.cp312-win_amd64.pyd
ninpol/_interpolator/grid.cpp
ninpol/_interpolator/grid.pxd
ninpol/_interpolator/grid.pyx
ninpol/_interpolator/interpolator.c
ninpol/_interpolator/interpolator.cp312-win_amd64.pyd
ninpol/_interpolator/interpolator.pxd
ninpol/_interpolator/interpolator.pyx
ninpol/_interpolator/logger.c
ninpol/_interpolator/logger.cp312-win_amd64.pyd
ninpol/_interpolator/logger.pxd
ninpol/_interpolator/logger.pyx
ninpol/_interpolator/ninpol_defines.pxd
ninpol/_methods/__init__.pxd
ninpol/_methods/gls.cp312-win_amd64.pyd
ninpol/_methods/gls.cpp
ninpol/_methods/gls.pxd
ninpol/_methods/gls.pyx
ninpol/_methods/idw.c
ninpol/_methods/idw.cp312-win_amd64.pyd
ninpol/_methods/idw.pxd
ninpol/_methods/idw.pyx
ninpol/_methods/lpew3.pxd
ninpol/_methods/lpew3.pyx
ninpol/_methods/ls.c
ninpol/_methods/ls.cp312-win_amd64.pyd
ninpol/_methods/ls.pxd
ninpol/_methods/ls.pyx
ninpol/utils/__init__.py
ninpol/utils/common.py
ninpol/utils/face_data_to_node.py
ninpol/utils/point_ordering.yaml
ninpol/utils/robin_hood.h
ninpol/utils/robin_hood.pxd
ninpol/windows/sys/time.h
ninpol-1.0.2.dist-info/LICENSE
ninpol-1.0.2.dist-info/METADATA
ninpol-1.0.2.dist-info/WHEEL
ninpol-1.0.2.dist-info/top_level.txt
ninpol-1.0.2.dist-info/RECORD
