Metadata-Version: 2.1
Name: ninpol
Version: 1.0.2
Summary: Library of Nodal Interpolation Techniques for Finite Volume Schemes
Author: Davi Yan
License:                     GNU GENERAL PUBLIC LICENSE
Keywords: finite volume,interpolation,mpfa
Requires: numpy
Requires: scipy
Requires: cython
Requires: meshio
Requires: pyyaml
Requires-Python: >=3.10
License-File: LICENSE
Requires-Dist: numpy
Requires-Dist: scipy
Requires-Dist: cython
Requires-Dist: meshio
Requires-Dist: pyyaml
Provides-Extra: dev
Requires-Dist: pytest; extra == "dev"
Requires-Dist: psutil; extra == "dev"
Requires-Dist: pytest_subtests; extra == "dev"
Requires-Dist: sympy; extra == "dev"
Requires-Dist: memory_profiler; extra == "dev"
